jk_ff.v
module jk_ff (
    input wire J,      // Entrada J
    input wire K,      // Entrada K
    input wire CLK,    // Sinal de clock
    input wire PR,     // Preload (ativo em nível lógico zero)
    input wire CLR,    // Clear (ativo em nível lógico zero)
    output reg Q,      // Saída Q
    output reg Qn      // Saída Q complementada
);

// Sempre que houver uma borda de subida no CLK
always @(posedge CLK or negedge PR or negedge CLR) begin
    if (!CLR) begin
        Q <= 0;      // Se CLR é ativado, Q é resetado para 0
    end else if (!PR) begin
        Q <= 1;      // Se PR é ativado, Q é setado para 1
    end else begin
        case ({J, K})
            2'b00: Q <= Q;      // Sem alteração
            2'b01: Q <= 0;      // Reset
            2'b10: Q <= 1;      // Set
            2'b11: Q <= ~Q;     // Toggle
        endcase
    end
end

// Saída complementada
always @(*) begin
    Qn = ~Q;
end

endmodule

d_ff.v
`include "jk_ff.v"

module d_ff (
    input wire D,      // Entrada D
    input wire CLK,    // Sinal de clock
    input wire PR,     // Preload (ativo em nível lógico zero)
    input wire CLR,    // Clear (ativo em nível lógico zero)
    output  Q,      // Saída Q
    output  Qn      // Saída Q complementada
);

    jk_ff uut    (
        .J(D),
        .K(~D),
        .CLK(CLK),
        .PR(PR),
        .CLR(CLR),
        .Q(Q),
        .Qn(Qn)
    );

endmodule

d_ff_tb.v
`timescale 1ns / 1ps
`include "d_ff.v"
module d_ff_tb;

    // Declaração de sinais
    reg D;
    reg CLK;
    reg PR;
    reg CLR;
    wire Q;
    wire Qn;

    // Instancia o módulo d_ff
    d_ff uut (
        .D(D),
        .CLK(CLK),
        .PR(PR),
        .CLR(CLR),
        .Q(Q),
        .Qn(Qn)
    );

    // Geração do clock
    initial begin
        CLK = 0;
        forever #5 CLK = ~CLK; // Clock de 10ns de período
    end

    // Teste das entradas
    initial begin
        // Inicializa sinais
        D = 0; PR = 0; CLR = 0;

        // Inicia o dump para o arquivo VCD
        $dumpfile("d_ff_tb.vcd");
        $dumpvars(0, d_ff_tb);

        // Teste com CLR e PR
        #10; 
        CLR = 1; // Ativa o Clear
        #10;
        CLR = 0; // Desativa o Clear
        #10;

        // Teste com PR
        PR = 1; // Ativa o Preload
        #10;
        PR = 0; // Desativa o Preload
        #10;

        // Teste da entrada D
        D = 1; // Define D como 1
        #10; // Espera um ciclo de clock

        D = 0; // Define D como 0
        #10; // Espera um ciclo de clock

        // Finaliza a simulação
        $finish;
    end

    // Monitoramento das saídas
    initial begin
        $monitor("Time = %0dns | D = %b | PR = %b | CLR = %b | Q = %b | Qn = %b", 
                 $time, D, PR, CLR, Q, Qn);
    end

endmodule

d_ff_tb.vcd
$date
	Mon Oct 28 11:07:26 2024
$end
$version
	Icarus Verilog
$end
$timescale
	1ps
$end
$scope module d_ff_tb $end
$var wire 1 ! Qn $end
$var wire 1 " Q $end
$var reg 1 # CLK $end
$var reg 1 $ CLR $end
$var reg 1 % D $end
$var reg 1 & PR $end
$scope module uut $end
$var wire 1 # CLK $end
$var wire 1 $ CLR $end
$var wire 1 % D $end
$var wire 1 & PR $end
$var wire 1 ! Qn $end
$var wire 1 " Q $end
$scope module uut $end
$var wire 1 # CLK $end
$var wire 1 $ CLR $end
$var wire 1 % J $end
$var wire 1 ' K $end
$var wire 1 & PR $end
$var reg 1 " Q $end
$var reg 1 ! Qn $end
$upscope $end
$upscope $end
$upscope $end
$enddefinitions $end
$comment Show the parameter values. $end
$dumpall
$end
#0
$dumpvars
1'
0&
0%
0$
0#
0"
1!
$end
#5000
1#
#10000
0#
1$
#15000
0!
1"
1#
#20000
1!
0"
0#
0$
#25000
1#
#30000
0#
1&
#35000
1#
#40000
0#
0&
#45000
1#
#50000
0'
0#
1%
#55000
1#
#60000
1'
0#
0%
