ex2.v
module amplificador(A, B, C, SA, SB, SC);

    input A, B, C;
    output SA, SB, SC;

    assign SA = A;
    assign SB = ~A & B;
    assign SC = ~A & ~B & C;
    

endmodule

ex2_tb.v
`timescale 1ns/1ns
`include "ex2.v"

module ex2_tb;

    reg A, B, C;
    wire SA, SB, SC;
    amplificador uut(A, B, C, SA, SB, SC);

    initial begin
        $dumpfile("ex2.vcd");
        $dumpvars(0, ex2_tb);

        A = 0; B = 0; C = 0; #20;
        A = 0; B = 1; C = 0; #20;
        A = 1; B = 0; C = 0; #20;
        A = 1; B = 1; C = 0; #20;
        A = 0; B = 0; C = 1; #20;
        A = 0; B = 1; C = 1; #20;
        A = 1; B = 0; C = 1; #20;
        A = 1; B = 1; C = 1; #20;

        $display("Teste completo");
    end

endmodule

ex2.vcd
$date
	Mon Sep 09 09:54:05 2024
$end
$version
	Icarus Verilog
$end
$timescale
	1ns
$end
$scope module ex2_tb $end
$var wire 1 ! SC $end
$var wire 1 " SB $end
$var wire 1 # SA $end
$var reg 1 $ A $end
$var reg 1 % B $end
$var reg 1 & C $end
$scope module uut $end
$var wire 1 $ A $end
$var wire 1 % B $end
$var wire 1 & C $end
$var wire 1 # SA $end
$var wire 1 " SB $end
$var wire 1 ! SC $end
$upscope $end
$upscope $end
$enddefinitions $end
$comment Show the parameter values. $end
$dumpall
$end
#0
$dumpvars
0&
0%
0$
0#
0"
0!
$end
#20
1"
1%
#40
0"
0%
1#
1$
#60
1%
#80
1!
1&
0%
0#
0$
#100
0!
1"
1%
#120
0"
0%
1#
1$
#140
1%
