ex3.v
module sistemaseguranca(P, W, M, S, A);

    input P, W, M, S;
    output A;

    assign A = (P & S) | (W & S) | M;


endmodule

ex3_tb.v
`timescale 1ns/1ns
`include "ex3.v"

module ex3_tb;

    reg P, W, M, S;
    wire A;
    sistemaseguranca uut(P, W, M, S, A);

    initial begin
        $dumpfile("ex3.vcd");
        $dumpvars(0, ex3_tb);

        P = 0; W = 0; M = 0; S = 0; #20;
        P = 0; W = 1; M = 0; S = 0; #20;
        P = 1; W = 0; M = 0; S = 0; #20;
        P = 1; W = 1; M = 0; S = 0; #20;
        P = 0; W = 0; M = 1; S = 0; #20;
        P = 0; W = 1; M = 1; S = 0; #20;
        P = 1; W = 0; M = 1; S = 0; #20;
        P = 1; W = 1; M = 1; S = 0; #20;
        P = 0; W = 0; M = 0; S = 1; #20;
        P = 0; W = 1; M = 0; S = 1; #20;
        P = 1; W = 0; M = 0; S = 1; #20;
        P = 1; W = 1; M = 0; S = 1; #20;
        P = 0; W = 0; M = 1; S = 1; #20;
        P = 0; W = 1; M = 1; S = 1; #20;
        P = 1; W = 0; M = 1; S = 1; #20;
        P = 1; W = 1; M = 1; S = 1; #20;

        $display("Teste completo");
    end

endmodule

ex3.vcd
$date
	Mon Sep 09 10:41:44 2024
$end
$version
	Icarus Verilog
$end
$timescale
	1ns
$end
$scope module ex3_tb $end
$var wire 1 ! A $end
$var reg 1 " M $end
$var reg 1 # P $end
$var reg 1 $ S $end
$var reg 1 % W $end
$scope module uut $end
$var wire 1 ! A $end
$var wire 1 " M $end
$var wire 1 # P $end
$var wire 1 $ S $end
$var wire 1 % W $end
$upscope $end
$upscope $end
$enddefinitions $end
$comment Show the parameter values. $end
$dumpall
$end
#0
$dumpvars
0%
0$
0#
0"
0!
$end
#20
1%
#40
0%
1#
#60
1%
#80
1!
1"
0%
0#
#100
1%
#120
0%
1#
#140
1%
#160
0!
1$
0"
0%
0#
#180
1!
1%
#200
0%
1#
#220
1%
#240
1"
0%
0#
#260
1%
#280
0%
1#
#300
1%
