jk_ff.v
module jk_ff (
    input wire J,      // Entrada J
    input wire K,      // Entrada K
    input wire CLK,    // Sinal de clock
    input wire PR,     // Preload (ativo em nível lógico zero)
    input wire CLR,    // Clear (ativo em nível lógico zero)
    output reg Q,      // Saída Q
    output reg Qn      // Saída Q complementada
);

// Sempre que houver uma borda de subida no CLK
always @(posedge CLK or negedge PR or negedge CLR) begin
    if (!CLR) begin
        Q <= 0;      // Se CLR é ativado, Q é resetado para 0
    end else if (!PR) begin
        Q <= 1;      // Se PR é ativado, Q é setado para 1
    end else begin
        case ({J, K})
            2'b00: Q <= Q;      // Sem alteração
            2'b01: Q <= 0;      // Reset
            2'b10: Q <= 1;      // Set
            2'b11: Q <= ~Q;     // Toggle
        endcase
    end
end

// Saída complementada
always @(*) begin
    Qn = ~Q;
end

endmodule

jk_ff_tb.v
`timescale 1ns / 1ps
`include "jk_ff.v"
module jk_ff_tb;

    // Declaração de sinais
    reg J;
    reg K;
    reg CLK;
    reg PR;
    reg CLR;
    wire Q;
    wire Qn;

    // Instancia o módulo jk_ff
    jk_ff uut (
        .J(J),
        .K(K),
        .CLK(CLK),
        .PR(PR),
        .CLR(CLR),
        .Q(Q),
        .Qn(Qn)
    );

    // Geração do clock
    initial begin
        CLK = 0;
        forever #5 CLK = ~CLK; // Clock de 10ns de período
    end

    // Teste das entradas
    initial begin
        // Inicializa sinais
        J = 0; K = 0; PR = 1; CLR = 1;

        // Inicia o dump para o arquivo VCD
        $dumpfile("jk_ff_tb.vcd");  // Nome do arquivo VCD
        $dumpvars(0, jk_ff_tb);      // Dump de todas as variáveis do testbench

        // Teste com PR e CLR
        #10; 
        CLR = 0; // Ativa o Clear
        #10;
        CLR = 1; // Desativa o Clear
        #10;

        // Teste com PR
        PR = 0; // Ativa o Preload
        #10;
        PR = 1; // Desativa o Preload
        #10;

        // Teste das entradas J e K
        J = 0; K = 0; // Nenhuma alteração
        #10;

        J = 0; K = 1; // Reset
        #10;

        J = 1; K = 0; // Set
        #10;

        J = 1; K = 1; // Toggle
        #10;

        $finish;

    end

endmodule

jk_ff_tb.vcd
$date
	Mon Oct 28 10:02:02 2024
$end
$version
	Icarus Verilog
$end
$timescale
	1ps
$end
$scope module jk_ff_tb $end
$var wire 1 ! Qn $end
$var wire 1 " Q $end
$var reg 1 # CLK $end
$var reg 1 $ CLR $end
$var reg 1 % J $end
$var reg 1 & K $end
$var reg 1 ' PR $end
$scope module uut $end
$var wire 1 # CLK $end
$var wire 1 $ CLR $end
$var wire 1 % J $end
$var wire 1 & K $end
$var wire 1 ' PR $end
$var reg 1 " Q $end
$var reg 1 ! Qn $end
$upscope $end
$upscope $end
$enddefinitions $end
$comment Show the parameter values. $end
$dumpall
$end
#0
$dumpvars
1'
0&
0%
1$
0#
x"
x!
$end
#5000
1#
#10000
1!
0"
0#
0$
#15000
1#
#20000
0#
1$
#25000
1#
#30000
0!
1"
0#
0'
#35000
1#
#40000
0#
1'
#45000
1#
#50000
0#
#55000
1#
#60000
0#
1&
#65000
1!
0"
1#
#70000
0#
0&
1%
#75000
0!
1"
1#
#80000
0#
1&
#85000
1!
0"
1#
