register_8bit.v
module register_8bit (
    input wire [7:0] D,   // Entrada de 8 bits
    input wire CLK,       // Sinal de clock
    input wire CLR,       // Sinal de Clear (ativo alto)
    output reg [7:0] Q    // Saída de 8 bits
);

// Geração dos flip-flops individuais
genvar i; // Declaração da variável de geração

generate
    for (i = 0; i < 8; i = i + 1) begin : ff_gen
        always @(posedge CLK or posedge CLR) begin
            if (CLR) begin
                Q[i] <= 1'b0; // Reset para 0
            end else begin
                if (CLK) // O D[i] só é considerado na borda de subida
                    Q[i] <= D[i]; // Armazena o valor da entrada D
            end
        end
    end
endgenerate

endmodule

register_8bit_tb.v
`timescale 1ns / 1ps
`include "register_8bit.v"

module register_8bit_tb;

    // Declaração de sinais
    reg [7:0] D;
    reg CLK;
    reg CLR;
    wire [7:0] Q;

    // Instancia o módulo register_8bit
    register_8bit uut (
        .D(D),
        .CLK(CLK),
        .CLR(CLR),
        .Q(Q)
    );

    // Geração do clock
    initial begin
        CLK = 0;
        forever #5 CLK = ~CLK; // Clock de 10ns de período
    end

    // Teste das entradas
    initial begin
        // Inicializa sinais
        D = 8'b00000000; 
        CLR = 0;

        // Inicia o dump para o arquivo VCD
        $dumpfile("register_8bit_tb.vcd");
        $dumpvars(0, register_8bit_tb);

        // Teste com CLR
        #10; 
        CLR = 1; // Ativa o Clear
        #10;
        CLR = 0; // Desativa o Clear
        #10;

        // Teste da entrada D
        D = 8'b10101010; // Define D
        #10; // Espera um ciclo de clock

        D = 8'b11110000; // Altera D
        #10; // Espera um ciclo de clock

        D = 8'b00001111; // Altera D novamente
        #10; // Espera um ciclo de clock

        // Finaliza a simulação
        $finish;
    end

    // Monitoramento das saídas
    initial begin
        $monitor("Time = %0dns | D = %b | CLR = %b | Q = %b", 
                 $time, D, CLR, Q);
    end

endmodule

register_8bit_tb.vcd
$date
	Mon Oct 28 11:10:24 2024
$end
$version
	Icarus Verilog
$end
$timescale
	1ps
$end
$scope module register_8bit_tb $end
$var wire 8 ! Q [7:0] $end
$var reg 1 " CLK $end
$var reg 1 # CLR $end
$var reg 8 $ D [7:0] $end
$scope module uut $end
$var wire 1 " CLK $end
$var wire 1 # CLR $end
$var wire 8 % D [7:0] $end
$var reg 8 & Q [7:0] $end
$scope begin ff_gen[0] $end
$var parameter 2 ' i $end
$upscope $end
$scope begin ff_gen[1] $end
$var parameter 2 ( i $end
$upscope $end
$scope begin ff_gen[2] $end
$var parameter 3 ) i $end
$upscope $end
$scope begin ff_gen[3] $end
$var parameter 3 * i $end
$upscope $end
$scope begin ff_gen[4] $end
$var parameter 4 + i $end
$upscope $end
$scope begin ff_gen[5] $end
$var parameter 4 , i $end
$upscope $end
$scope begin ff_gen[6] $end
$var parameter 4 - i $end
$upscope $end
$scope begin ff_gen[7] $end
$var parameter 4 . i $end
$upscope $end
$upscope $end
$upscope $end
$enddefinitions $end
$comment Show the parameter values. $end
$dumpall
b111 .
b110 -
b101 ,
b100 +
b11 *
b10 )
b1 (
b0 '
$end
#0
$dumpvars
bx &
b0 %
b0 $
0#
0"
bx !
$end
#5000
b0 !
b0 &
1"
#10000
0"
1#
#15000
1"
#20000
0"
0#
#25000
1"
#30000
0"
b10101010 $
b10101010 %
#35000
b10101010 !
b10101010 &
1"
#40000
0"
b11110000 $
b11110000 %
#45000
b11110000 !
b11110000 &
1"
#50000
0"
b1111 $
b1111 %
#55000
b1111 !
b1111 &
1"
